habana_frameworks/medialoaders/__init__.py
habana_frameworks/medialoaders/torch/__init__.py
habana_frameworks/medialoaders/torch/media_dataloader_mediapipe.py
habana_frameworks/medialoaders/torch/mediapipe_next_gpt.py
habana_frameworks/medialoaders/torch/mediapipe_ssd.py
habana_frameworks/medialoaders/torch/mediapipe_unet.py
habana_frameworks/medialoaders/torch/mediapipe_unet_3d.py
habana_frameworks/medialoaders/torch/mediapipe_unet_3d_bf16.py
habana_frameworks/medialoaders/torch/mediapipe_unet_3d_cpp.py
habana_frameworks/medialoaders/torch/mediapipe_unet_3d_cpp_bf16.py
habana_frameworks/medialoaders/torch/mediapipe_unet_cpp.py
habana_frameworks/mediapipe/__init__.py
habana_frameworks/mediapipe/fn.py
habana_frameworks/mediapipe/media_proxy.py
habana_frameworks/mediapipe/media_types.py
habana_frameworks/mediapipe/mediapipe.py
habana_frameworks/mediapipe/backend/__init__.py
habana_frameworks/mediapipe/backend/cal.py
habana_frameworks/mediapipe/backend/graph.py
habana_frameworks/mediapipe/backend/graph_legacy.py
habana_frameworks/mediapipe/backend/iterator.py
habana_frameworks/mediapipe/backend/legacy.py
habana_frameworks/mediapipe/backend/logger.py
habana_frameworks/mediapipe/backend/nodes.py
habana_frameworks/mediapipe/backend/operator_specs.py
habana_frameworks/mediapipe/backend/proxy_impl.py
habana_frameworks/mediapipe/backend/tensor.py
habana_frameworks/mediapipe/backend/tensor_legacy.py
habana_frameworks/mediapipe/backend/tracing.py
habana_frameworks/mediapipe/backend/utils.py
habana_frameworks/mediapipe/include/media_pytorch_proxy.h
habana_frameworks/mediapipe/operators/__init__.py
habana_frameworks/mediapipe/operators/media_nodes.py
habana_frameworks/mediapipe/operators/media_params.py
habana_frameworks/mediapipe/operators/media_schema.py
habana_frameworks/mediapipe/operators/complex_nodes/__init__.py
habana_frameworks/mediapipe/operators/complex_nodes/complex_node_params.py
habana_frameworks/mediapipe/operators/complex_nodes/complex_node_schema.py
habana_media_loader-1.23.0.695.dist-info/LICENSE.txt
habana_media_loader-1.23.0.695.dist-info/METADATA
habana_media_loader-1.23.0.695.dist-info/WHEEL
habana_media_loader-1.23.0.695.dist-info/top_level.txt
habana_media_loader-1.23.0.695.dist-info/RECORD
