Metadata-Version: 2.1
Name: habana-media-loader
Version: 1.23.0.695
Summary: Dataloader using Habana hardware media pipeline
Home-page: https://habana.ai/
Author: Habana Labs Ltd., an Intel Company
Author-email: support@habana.ai
License: See LICENSE.txt
Platform: UNKNOWN
License-File: LICENSE.txt
Requires-Dist: pillow-simd
Requires-Dist: tqdm
Requires-Dist: av (==12.1.0)
